setup.py
nats/__init__.py
nats/client.py
nats/common.py
nats/connector.py
nats/error.py
nats/heartbeat.py
nats/protocol.py
nats/stat.py
python_nats.egg-info/PKG-INFO
python_nats.egg-info/SOURCES.txt
python_nats.egg-info/dependency_links.txt
python_nats.egg-info/top_level.txt
test/__init__.py
test/fixtures.py
test/test_integration.py
test/test_unit.py