Metadata-Version: 1.0
Name: python-nats
Version: 0.1.0.beta.1
Summary: python client for nats message bus
Home-page: https://github.com/jackytu/python-nats
Author: TuZhongying(Jacky Tu)
Author-email: zhongying.tu@gmail.com
License: MIT
Keywords: python,nats
Platform: Independant
